five_tree_wood/__init__.py
five_tree_wood/ai/__init__.py
five_tree_wood/ai/__main__.py
five_tree_wood/ai/config.py
five_tree_wood/ai/main.py
five_tree_wood/ai/aircon/__init__.py
five_tree_wood/ai/aircon/predict.py
five_tree_wood/ai/aircon/train.py
five_tree_wood/ai/conf/__init__.py
five_tree_wood/ai/conf/config.py
five_tree_wood_ai-1.0.1.dist-info/licenses/LICENSE
ninjateaparty/ai/config.py
ninjateaparty/ai/aircon/predict.py
ninjateaparty/ai/aircon/train.py
ninjateaparty/ai/conf/__init__.py
ninjateaparty/ai/conf/config.py
five_tree_wood_ai-1.0.1.dist-info/METADATA
five_tree_wood_ai-1.0.1.dist-info/WHEEL
five_tree_wood_ai-1.0.1.dist-info/entry_points.txt
five_tree_wood_ai-1.0.1.dist-info/top_level.txt
five_tree_wood_ai-1.0.1.dist-info/RECORD
