Metadata-Version: 2.4
Name: five-tree-wood-ai
Version: 1.0.1
Summary: Five Tree Wood AI - AI utilities for home assistant
Author-email: Penny Wood <github@ninjateaparty.com>
License-Expression: MIT
Project-URL: Homepage, https://github.com/ninjateaparty/aircon-ai
Project-URL: Repository, https://github.com/ninjateaparty/aircon-ai
Classifier: Development Status :: 4 - Beta
Classifier: Intended Audience :: Developers
Classifier: Programming Language :: Python :: 3
Classifier: Programming Language :: Python :: 3.12
Requires-Python: >=3.12
License-File: LICENSE
Requires-Dist: pandas>=2.3
Requires-Dist: scikit_learn>=1.7
Requires-Dist: packaging>=25.0
Requires-Dist: influxdb-client>=1.49
Requires-Dist: flask>=3.1.2
Provides-Extra: dev
Requires-Dist: black>=24.0; extra == "dev"
Requires-Dist: isort>=5.13; extra == "dev"
Requires-Dist: pylint>=3.2; extra == "dev"
Requires-Dist: autopep8>=2.3; extra == "dev"
Requires-Dist: pytest>=8.0; extra == "dev"
Dynamic: license-file
